<?xml version="1.0"?>
<WeeklyTop xmlns:xsi="http://www.w3.org/2001/XMLSchema-instance" xmlns:xsd="http://www.w3.org/2001/XMLSchema">
  <WeekNo>8</WeekNo>
  <TopProcessed>false</TopProcessed>
  <ItemType>Track</ItemType>
  <TopItems>
    <TopItem>
      <Rank>1</Rank>
      <NumberOfPlays>4</NumberOfPlays>
      <ItemName>Gudrid Hansdottir - Stjornur</ItemName>
      <ItemType>Track</ItemType>
      <Score>0</Score>
      <EntryWeek>0</EntryWeek>
    </TopItem>
    <TopItem>
      <Rank>2</Rank>
      <NumberOfPlays>3</NumberOfPlays>
      <ItemName>Belle and Sebastian - I Didn't See It Coming</ItemName>
      <ItemType>Track</ItemType>
      <Score>0</Score>
      <EntryWeek>0</EntryWeek>
    </TopItem>
    <TopItem>
      <Rank>3</Rank>
      <NumberOfPlays>3</NumberOfPlays>
      <ItemName>Paloma Faith - Do You Want The Truth Or Something Beautiful?</ItemName>
      <ItemType>Track</ItemType>
      <Score>0</Score>
      <EntryWeek>0</EntryWeek>
    </TopItem>
    <TopItem>
      <Rank>4</Rank>
      <NumberOfPlays>3</NumberOfPlays>
      <ItemName>The Royal Family and the Poor - I Love You</ItemName>
      <ItemType>Track</ItemType>
      <Score>0</Score>
      <EntryWeek>0</EntryWeek>
    </TopItem>
    <TopItem>
      <Rank>5</Rank>
      <NumberOfPlays>3</NumberOfPlays>
      <ItemName>Suede - Saturday Night</ItemName>
      <ItemType>Track</ItemType>
      <Score>0</Score>
      <EntryWeek>0</EntryWeek>
    </TopItem>
    <TopItem>
      <Rank>6</Rank>
      <NumberOfPlays>3</NumberOfPlays>
      <ItemName>Ultramarine - Weird Gear</ItemName>
      <ItemType>Track</ItemType>
      <Score>0</Score>
      <EntryWeek>0</EntryWeek>
    </TopItem>
    <TopItem>
      <Rank>7</Rank>
      <NumberOfPlays>2</NumberOfPlays>
      <ItemName>The Flys - Love and a molotov cocktail</ItemName>
      <ItemType>Track</ItemType>
      <Score>0</Score>
      <EntryWeek>0</EntryWeek>
    </TopItem>
    <TopItem>
      <Rank>8</Rank>
      <NumberOfPlays>2</NumberOfPlays>
      <ItemName>Pixies - I Can't Forget</ItemName>
      <ItemType>Track</ItemType>
      <Score>0</Score>
      <EntryWeek>0</EntryWeek>
    </TopItem>
    <TopItem>
      <Rank>9</Rank>
      <NumberOfPlays>2</NumberOfPlays>
      <ItemName>Magazine - Light Pours Out of Me</ItemName>
      <ItemType>Track</ItemType>
      <Score>0</Score>
      <EntryWeek>0</EntryWeek>
    </TopItem>
    <TopItem>
      <Rank>10</Rank>
      <NumberOfPlays>2</NumberOfPlays>
      <ItemName>Paolo Nutini - These Streets</ItemName>
      <ItemType>Track</ItemType>
      <Score>0</Score>
      <EntryWeek>0</EntryWeek>
    </TopItem>
  </TopItems>
</WeeklyTop>